[
  {
    "name": "手机数码",
    "icon": "📱",
    "sort": 1,
    "status": 1,
    "created_at": 1783784214,
    "id": 1
  },
  {
    "name": "电脑办公",
    "icon": "💻",
    "sort": 2,
    "status": 1,
    "created_at": 1783784214,
    "id": 2
  },
  {
    "name": "家用电器",
    "icon": "🔌",
    "sort": 3,
    "status": 1,
    "created_at": 1783784214,
    "id": 3
  },
  {
    "name": "服饰鞋包",
    "icon": "👜",
    "sort": 4,
    "status": 1,
    "created_at": 1783784214,
    "id": 4
  },
  {
    "name": "美妆个护",
    "icon": "💄",
    "sort": 5,
    "status": 1,
    "created_at": 1783784214,
    "id": 5
  },
  {
    "name": "食品生鲜",
    "icon": "🍎",
    "sort": 6,
    "status": 1,
    "created_at": 1783784214,
    "id": 6
  },
  {
    "name": "家居家装",
    "icon": "🛋️",
    "sort": 7,
    "status": 1,
    "created_at": 1783784214,
    "id": 7
  },
  {
    "name": "运动户外",
    "icon": "⚽",
    "sort": 8,
    "status": 1,
    "created_at": 1783784214,
    "id": 8
  }
]